squid/__init__.py
squid/ml_logging/__init__.py
squid/ml_logging/loggers.py
squid/ml_logging/utils.py
squid/server/__init__.py
squid/server/operations.py
squid/server/utils.py
squid/server/infra/.env
squid/server/infra/clean-infra.sh
squid/server/infra/docker-compose.yaml
squid/server/infra/minio/create-bucket.sh
squid/server/infra/mlflow_server/Dockerfile
squid/server/infra/postgres/init.sql
squid_ml-0.1.2.dist-info/licenses/LICENSE
squid_ml-0.1.2.dist-info/METADATA
squid_ml-0.1.2.dist-info/WHEEL
squid_ml-0.1.2.dist-info/top_level.txt
squid_ml-0.1.2.dist-info/RECORD
